deeptrack/__init__.py
deeptrack/aberrations.py
deeptrack/augmentations.py
deeptrack/elementwise.py
deeptrack/features.py
deeptrack/holography.py
deeptrack/image.py
deeptrack/math.py
deeptrack/noises.py
deeptrack/optics.py
deeptrack/properties.py
deeptrack/scatterers.py
deeptrack/sequences.py
deeptrack/statistics.py
deeptrack/types.py
deeptrack/utils.py
deeptrack/backend/__init__.py
deeptrack/backend/_config.py
deeptrack/backend/core.py
deeptrack/backend/mie.py
deeptrack/backend/pint_definition.py
deeptrack/backend/polynomials.py
deeptrack/backend/units.py
deeptrack/deeplay/__init__.py
deeptrack/extras/__init__.py
deeptrack/extras/radialcenter.py
deeptrack/pytorch/__init__.py
deeptrack/pytorch/data.py
deeptrack/pytorch/features.py
deeptrack/sources/__init__.py
deeptrack/sources/base.py
deeptrack/sources/folder.py
deeptrack/sources/rng.py
deeptrack/tests/__init__.py
deeptrack/tests/test_aberrations.py
deeptrack/tests/test_augmentations.py
deeptrack/tests/test_elementwise.py
deeptrack/tests/test_features.py
deeptrack/tests/test_holography.py
deeptrack/tests/test_image.py
deeptrack/tests/test_math.py
deeptrack/tests/test_noises.py
deeptrack/tests/test_optics.py
deeptrack/tests/test_properties.py
deeptrack/tests/test_scatterers.py
deeptrack/tests/test_sequences.py
deeptrack/tests/test_statistics.py
deeptrack/tests/test_utils.py
deeptrack/tests/backend/__init__.py
deeptrack/tests/backend/test_core.py
deeptrack/tests/backend/test_mie.py
deeptrack/tests/backend/test_polynomials.py
deeptrack/tests/extras/__init__.py
deeptrack/tests/extras/test_radialcenter.py
deeptrack-2.0.1.dist-info/METADATA
deeptrack-2.0.1.dist-info/WHEEL
deeptrack-2.0.1.dist-info/top_level.txt
deeptrack-2.0.1.dist-info/RECORD
