Metadata-Version: 2.4
Name: deeptrack
Version: 2.0.1
Summary: A deep learning framework to enhance microscopy, developed by DeepTrackAI.
Home-page: https://github.com/DeepTrackAI/DeepTrack2
Author: Benjamin Midtvedt, Jesus Pineda, Henrik Klein Moberg, Harshith Bachimanchi, Mirja Granfors, Alex Lech, Carlo Manzo, Giovanni Volpe
License: MIT
Classifier: Programming Language :: Python :: 3
Classifier: License :: OSI Approved :: MIT License
Classifier: Operating System :: OS Independent
Requires-Python: >=3.8
Requires-Dist: numpy
Requires-Dist: matplotlib
Requires-Dist: scipy
Requires-Dist: scikit-image
Requires-Dist: more_itertools
Requires-Dist: pint
Requires-Dist: pandas
Requires-Dist: tqdm
Requires-Dist: lazy_import
Requires-Dist: rich
Requires-Dist: gdown
Dynamic: author
Dynamic: classifier
Dynamic: description
Dynamic: description-content-type
Dynamic: home-page
Dynamic: license
Dynamic: requires-dist
Dynamic: requires-python
Dynamic: summary
